django_masterpass/__init__.py
django_masterpass/apps.py
django_masterpass/auth.py
django_masterpass/tests.py
django_masterpass-0.0.1.dist-info/LICENSE
django_masterpass-0.0.1.dist-info/METADATA
django_masterpass-0.0.1.dist-info/WHEEL
django_masterpass-0.0.1.dist-info/top_level.txt
django_masterpass-0.0.1.dist-info/RECORD
