Metadata-Version: 2.1
Name: django-masterpass
Version: 0.0.1
Summary: Django master password
Home-page: https://github.com/ulkoart/django-masterpass
Author: Artem Ulko
Author-email: ulkoart@gmail.com
License: MIT
Keywords: django master password authentication authentication_backends
Platform: UNKNOWN
Requires-Dist: Django
